whl_setup.py
whl.setup-0.2.dist-info/top_level.txt
whl.setup-0.2.dist-info/entry_points.txt
whl.setup-0.2.dist-info/METADATA
whl.setup-0.2.dist-info/DESCRIPTION.rst
whl.setup-0.2.dist-info/metadata.json
whl.setup-0.2.dist-info/WHEEL
whl.setup-0.2.dist-info/RECORD
