Metadata-Version: 2.0
Name: whl.setup
Version: 0.2
Summary: a pip based replacement for ez_setup and setup_requires
Home-page: https://github.com/RonnyPfannschmidt/whl_setup
Author: Ronny Pfannschmidt
Author-email: opensource+whl.setup@ronnypfannschmidt.de
License: UNKNOWN
Platform: UNKNOWN
